verse_content_sdk/__init__.py
verse_content_sdk/audio/__init__.py
verse_content_sdk/audio/generate_audio.py
verse_content_sdk/cli/__init__.py
verse_content_sdk/cli/generate.py
verse_content_sdk/deployment/__init__.py
verse_content_sdk/deployment/deploy.py
verse_content_sdk/embeddings/__init__.py
verse_content_sdk/embeddings/generate_embeddings.py
verse_content_sdk/embeddings/generate_embeddings_local.py
verse_content_sdk/embeddings/local_embeddings.py
verse_content_sdk/images/__init__.py
verse_content_sdk/images/generate_theme_images.py
verse_content_sdk/utils/__init__.py
verse_content_sdk/utils/file_utils.py
verse_content_sdk/utils/yaml_parser.py
verse_content_sdk-0.2.0.dist-info/licenses/LICENSE
verse_content_sdk-0.2.0.dist-info/METADATA
verse_content_sdk-0.2.0.dist-info/WHEEL
verse_content_sdk-0.2.0.dist-info/entry_points.txt
verse_content_sdk-0.2.0.dist-info/top_level.txt
verse_content_sdk-0.2.0.dist-info/RECORD
